netifaces2-0.0.22.dist-info/METADATA
netifaces2-0.0.22.dist-info/WHEEL
netifaces2-0.0.22.dist-info/license_files/LICENSE
netifaces/__init__.py
netifaces/defs.py
netifaces/routes.py
netifaces/py.typed
netifaces/netifaces.abi3.so
netifaces2-0.0.22.dist-info/RECORD
