Metadata-Version: 2.1
Name: netifaces2
Version: 0.0.22
Classifier: Programming Language :: Rust
Classifier: Programming Language :: Python :: Implementation :: CPython
Classifier: Programming Language :: Python :: Implementation :: PyPy
Classifier: License :: OSI Approved :: MIT License
Classifier: Operating System :: POSIX :: Linux
Classifier: Operating System :: MacOS
Classifier: Operating System :: Microsoft :: Windows
Classifier: Topic :: System :: Networking
Requires-Dist: typing-extensions ; python_version < '3.8'
Requires-Dist: mypy >=0.991 ; extra == 'dev'
Requires-Dist: black >=23.1.0 ; extra == 'dev'
Requires-Dist: ruff >=0.0.240 ; extra == 'dev'
Requires-Dist: pytest >=7.1.1 ; extra == 'dev'
Provides-Extra: dev
License-File: LICENSE
Summary: Portable network interface information
Author-email: Samuel Yvon <samuelyvon9@gmail.com>
Maintainer-email: Samuel Yvon <samuelyvon9@gmail.com>
Requires-Python: >=3.7
Project-URL: Homepage, https://github.com/SamuelYvon/netifaces-2
Project-URL: Issues, https://github.com/SamuelYvon/netifaces-2/issues
